starlette_dispatch/__init__.py
starlette_dispatch/injections.py
starlette_dispatch/py.typed
starlette_dispatch/route_group.py
starlette_dispatch/contrib/__init__.py
starlette_dispatch/contrib/dependencies.py
starlette_dispatch-0.27.2.dist-info/METADATA
starlette_dispatch-0.27.2.dist-info/WHEEL
starlette_dispatch-0.27.2.dist-info/licenses/LICENSE
starlette_dispatch-0.27.2.dist-info/RECORD
